fasteryoutubesummary/__init__.py
fasteryoutubesummary/caption.py
fasteryoutubesummary/cli.py
fasteryoutubesummary/example.py
fasteryoutubesummary/generate_webpage.py
fasteryoutubesummary/get_video_summary.py
fasteryoutubesummary-3.1.0.dist-info/LICENSE
fasteryoutubesummary-3.1.0.dist-info/METADATA
fasteryoutubesummary-3.1.0.dist-info/WHEEL
fasteryoutubesummary-3.1.0.dist-info/entry_points.txt
fasteryoutubesummary-3.1.0.dist-info/top_level.txt
fasteryoutubesummary-3.1.0.dist-info/RECORD
