Metadata-Version: 2.1
Name: fasteryoutubesummary
Version: 3.1.0
Summary: Faster YouTube Summary is a tool designed to quickly generate detailed summaries of YouTube videos using Groq API
Home-page: https://github.com/AlexanderJiazx/FasterYouTubeSummary
Author: Alexander Jia
Author-email: hellolightning321@gmail.com
Classifier: Programming Language :: Python :: 3
Classifier: License :: OSI Approved :: MIT License
Classifier: Operating System :: OS Independent
Requires-Python: >=3.11
License-File: LICENSE
Requires-Dist: pytubefix
Requires-Dist: groq
Requires-Dist: requests
Requires-Dist: click
